sjtu_schedule_exporter_cli/__init__.py
sjtu_schedule_exporter_cli/__main__.py
sjtu_schedule_exporter_cli/calendar.py
sjtu_schedule_exporter_cli/tui.py
sjtu_schedule_exporter_cli/utils.py
sjtu_schedule_exporter_cli-0.1.2.dist-info/LICENSE.md
sjtu_schedule_exporter_cli-0.1.2.dist-info/METADATA
sjtu_schedule_exporter_cli-0.1.2.dist-info/WHEEL
sjtu_schedule_exporter_cli-0.1.2.dist-info/entry_points.txt
sjtu_schedule_exporter_cli-0.1.2.dist-info/top_level.txt
sjtu_schedule_exporter_cli-0.1.2.dist-info/RECORD
