Metadata-Version: 2.1
Name: sjtu-schedule-exporter-cli
Version: 0.1.2
Summary: A simple utility to export your SJTU schedule in ICS format
Home-page: https://github.com/PhotonQuantum/sjtu-schedule-exporter-cli
Author: LightQuantum
Author-email: self@lightquantum.me
License: UNKNOWN
Platform: UNKNOWN
Classifier: Operating System :: OS Independent
Classifier: Programming Language :: Python :: 3.7
Classifier: Programming Language :: Python :: 3.8
Classifier: Programming Language :: Python :: 3 :: Only
Classifier: License :: OSI Approved :: GNU General Public License v3 (GPLv3)
Classifier: Environment :: Web Environment
Classifier: Intended Audience :: End Users/Desktop
Classifier: Topic :: Internet :: WWW/HTTP :: Dynamic Content
Requires-Dist: pysjtu
Requires-Dist: blessed
Requires-Dist: ics
Requires-Dist: arrow (<0.15)
